pytorch_helper/__init__.py
pytorch_helper/layers/__init__.py
pytorch_helper/layers/dict_to_parameters.py
pytorch_helper/layers/dot_product.py
pytorch_helper/layers/gru_last_hidden_state.py
pytorch_helper/layers/hidden_state_reset_gru.py
pytorch_helper/layers/hidden_state_reset_lstm.py
pytorch_helper/layers/hidden_state_reset_rnn.py
pytorch_helper/layers/lazily_initialized_linear.py
pytorch_helper/layers/lstm_last_hidden_state.py
pytorch_helper/layers/permute.py
pytorch_helper/layers/reshape.py
pytorch_helper/layers/rnn_last_hidden_state.py
pytorch_helper/layers/select_from_array.py
pytorch_helper/utils/__init__.py
pytorch_helper/utils/text.py
pytorch_helper/utils/time_series.py
pytorch_helper-0.0.14.dist-info/METADATA
pytorch_helper-0.0.14.dist-info/WHEEL
pytorch_helper-0.0.14.dist-info/top_level.txt
pytorch_helper-0.0.14.dist-info/RECORD
