Metadata-Version: 2.1
Name: pytorch-helper
Version: 0.0.14
Summary: Pytorch helper
Home-page: https://github.com/automatethem/pytorch-helper
Author: Sang Ki Kwon
Author-email: automatethem@gmail.com
License: MIT
Platform: UNKNOWN
Requires-Dist: torchsummaryX
